canvalib/__init__.py
canvalib/canvalib.py
canvalib-0.0.7.dist-info/licenses/LICENSE
canvalib-0.0.7.dist-info/METADATA
canvalib-0.0.7.dist-info/WHEEL
canvalib-0.0.7.dist-info/top_level.txt
canvalib-0.0.7.dist-info/RECORD
