Metadata-Version: 2.4
Name: canvalib
Version: 0.0.7
Summary: Canva-like library for terminal
Author-email: danb1551 <danielbalcar22@gmail.com>
License: Copyright 2025 danb1551
Project-URL: Homepage, https://github.com/danb1551/canvalib
Project-URL: Issues, https://github.com/danb1551/canvalib/issues
Classifier: Programming Language :: Python :: 3
Classifier: Operating System :: OS Independent
Classifier: Natural Language :: Czech
Classifier: Topic :: Terminals
Classifier: Topic :: Utilities
Requires-Python: >=3.9
License-File: LICENSE
Requires-Dist: colorama>=0.4.6
Dynamic: license-file
